{
	"cmake" : 
	{
		"generator" : 
		{
			"multiConfig" : false,
			"name" : "Unix Makefiles"
		},
		"paths" : 
		{
			"cmake" : "/opt/homebrew/Cellar/cmake/3.29.3/bin/cmake",
			"cpack" : "/opt/homebrew/Cellar/cmake/3.29.3/bin/cpack",
			"ctest" : "/opt/homebrew/Cellar/cmake/3.29.3/bin/ctest",
			"root" : "/opt/homebrew/Cellar/cmake/3.29.3/share/cmake"
		},
		"version" : 
		{
			"isDirty" : false,
			"major" : 3,
			"minor" : 29,
			"patch" : 3,
			"string" : "3.29.3",
			"suffix" : ""
		}
	},
	"objects" : 
	[
		{
			"jsonFile" : "codemodel-v2-49f1ef3321847f04e3a8.json",
			"kind" : "codemodel",
			"version" : 
			{
				"major" : 2,
				"minor" : 7
			}
		},
		{
			"jsonFile" : "cache-v2-8400a580459f03c4c4a4.json",
			"kind" : "cache",
			"version" : 
			{
				"major" : 2,
				"minor" : 0
			}
		},
		{
			"jsonFile" : "cmakeFiles-v1-e52f05e6b030f5ba0dcb.json",
			"kind" : "cmakeFiles",
			"version" : 
			{
				"major" : 1,
				"minor" : 0
			}
		},
		{
			"jsonFile" : "toolchains-v1-0a091cee1530a5df8f5c.json",
			"kind" : "toolchains",
			"version" : 
			{
				"major" : 1,
				"minor" : 0
			}
		}
	],
	"reply" : 
	{
		"client-vscode" : 
		{
			"query.json" : 
			{
				"requests" : 
				[
					{
						"kind" : "cache",
						"version" : 2
					},
					{
						"kind" : "codemodel",
						"version" : 2
					},
					{
						"kind" : "toolchains",
						"version" : 1
					},
					{
						"kind" : "cmakeFiles",
						"version" : 1
					}
				],
				"responses" : 
				[
					{
						"jsonFile" : "cache-v2-8400a580459f03c4c4a4.json",
						"kind" : "cache",
						"version" : 
						{
							"major" : 2,
							"minor" : 0
						}
					},
					{
						"jsonFile" : "codemodel-v2-49f1ef3321847f04e3a8.json",
						"kind" : "codemodel",
						"version" : 
						{
							"major" : 2,
							"minor" : 7
						}
					},
					{
						"jsonFile" : "toolchains-v1-0a091cee1530a5df8f5c.json",
						"kind" : "toolchains",
						"version" : 
						{
							"major" : 1,
							"minor" : 0
						}
					},
					{
						"jsonFile" : "cmakeFiles-v1-e52f05e6b030f5ba0dcb.json",
						"kind" : "cmakeFiles",
						"version" : 
						{
							"major" : 1,
							"minor" : 0
						}
					}
				]
			}
		}
	}
}
